packagedemo/__init__.py
packagedemo/main.py
packagedemo-2015.09.1.dist-info/METADATA
packagedemo-2015.09.1.dist-info/RECORD
packagedemo-2015.09.1.dist-info/metadata.json
packagedemo-2015.09.1.dist-info/WHEEL
packagedemo-2015.09.1.dist-info/top_level.txt
packagedemo-2015.09.1.dist-info/DESCRIPTION.rst
