Metadata-Version: 2.0
Name: packagedemo
Version: 2015.09.1
Summary: A demo for python packaging.
Home-page: https://github.com/DeliangFan/packagedemo
Author: vanderliang
Author-email: vanderliang@gmail.com
License: MIT
Keywords: demo
Platform: UNKNOWN
